thepuzzlecell/__init__.py
thepuzzlecell-0.0.4.dist-info/LICENSE
thepuzzlecell-0.0.4.dist-info/METADATA
thepuzzlecell-0.0.4.dist-info/WHEEL
thepuzzlecell-0.0.4.dist-info/top_level.txt
thepuzzlecell-0.0.4.dist-info/RECORD
