Metadata-Version: 2.1
Name: thepuzzlecell
Version: 0.0.4
Summary: This package allows you to connect to TPC servers as a client and send packets.
Home-page: https://github.com/milena-kos/thepuzzlecell-client-py
Author: Milenakos
Author-email: rozhitsyn2015@yandex.ru
License: UNKNOWN
Project-URL: Bug Tracker, https://github.com/milena-kos/thepuzzlecell-client-py/issues
Platform: UNKNOWN
Classifier: Programming Language :: Python :: 3
Classifier: License :: OSI Approved :: The Unlicense (Unlicense)
Classifier: Operating System :: OS Independent
Requires-Python: >=3.0
License-File: LICENSE
Requires-Dist: asyncio
Requires-Dist: websockets
